{"trading_day":"20260618","themes":[{"name":"반도체 대표주(생산)","no":"155","total_score":78.7,"rank_at_forecast":1},{"name":"IT 대표주","no":"173","total_score":77.9,"rank_at_forecast":2},{"name":"온디바이스 AI","no":"545","total_score":76.0,"rank_at_forecast":3},{"name":"뉴로모픽 반도체","no":"556","total_score":75.2,"rank_at_forecast":4},{"name":"HBM(고대역폭메모리)","no":"536","total_score":69.2,"rank_at_forecast":5},{"name":"제습기","no":"328","total_score":68.5,"rank_at_forecast":6},{"name":"전력반도체","no":"533","total_score":68.2,"rank_at_forecast":7},{"name":"아이폰","no":"388","total_score":67.3,"rank_at_forecast":8},{"name":"핵융합에너지","no":"187","total_score":66.3,"rank_at_forecast":9},{"name":"전력설비","no":"123","total_score":65.4,"rank_at_forecast":10},{"name":"소캠(SOCAMM)","no":"599","total_score":65.3,"rank_at_forecast":11},{"name":"CXL(컴퓨트익스프레스링크)","no":"547","total_score":64.5,"rank_at_forecast":12},{"name":"시멘트/레미콘","no":"44","total_score":63.5,"rank_at_forecast":13},{"name":"마이크로 LED","no":"390","total_score":63.2,"rank_at_forecast":14},{"name":"LED장비","no":"269","total_score":62.9,"rank_at_forecast":15},{"name":"건설 중소형","no":"322","total_score":62.9,"rank_at_forecast":16},{"name":"페라이트","no":"534","total_score":61.7,"rank_at_forecast":17},{"name":"니켈","no":"511","total_score":61.7,"rank_at_forecast":18},{"name":"철강 중소형","no":"72","total_score":60.7,"rank_at_forecast":19},{"name":"스마트카(SMART CAR)","no":"332","total_score":60.4,"rank_at_forecast":20},{"name":"생명보험","no":"283","total_score":60.2,"rank_at_forecast":21},{"name":"日 수출 규제(국산화 등)","no":"422","total_score":58.3,"rank_at_forecast":22},{"name":"희귀금속(희토류 등)","no":"298","total_score":57.6,"rank_at_forecast":23},{"name":"스마트그리드(지능형전력망)","no":"229","total_score":57.5,"rank_at_forecast":24},{"name":"시스템반도체","no":"307","total_score":56.9,"rank_at_forecast":25},{"name":"마리화나(대마)","no":"408","total_score":55.7,"rank_at_forecast":26},{"name":"반도체 기판(FC-BGA/PCB/MLB 등)","no":"608","total_score":55.3,"rank_at_forecast":27},{"name":"남북경협","no":"121","total_score":55.2,"rank_at_forecast":28},{"name":"MLCC(적층세라믹콘덴서)","no":"405","total_score":55.1,"rank_at_forecast":29},{"name":"반도체 재료/부품","no":"14","total_score":55.0,"rank_at_forecast":30}]}