{"trading_day":"20260708","stocks":[{"code":"036630","name":"세종텔레콤","market":"KOSDAQ","price":8810,"change":7.44,"ratio":99.88,"volume":1086037},{"code":"014970","name":"삼륭물산","market":"KOSDAQ","price":4550,"change":-0.22,"ratio":85.14,"volume":900219},{"code":"024060","name":"흥구석유","market":"KOSDAQ","price":10440,"change":14.73,"ratio":61.77,"volume":10933274},{"code":"037230","name":"한국팩키지","market":"KOSDAQ","price":1418,"change":-0.42,"ratio":60.5,"volume":2103415},{"code":"049480","name":"오픈베이스","market":"KOSDAQ","price":1900,"change":3.88,"ratio":53.94,"volume":5646451},{"code":"029480","name":"광무","market":"KOSDAQ","price":1580,"change":10.1,"ratio":50.18,"volume":6153997},{"code":"004090","name":"한국석유","market":"KOSPI","price":10920,"change":0.09,"ratio":49.76,"volume":2136435},{"code":"285800","name":"진영","market":"KOSDAQ","price":921,"change":11.77,"ratio":43.74,"volume":2980076},{"code":"038870","name":"에코심플렉스","market":"KOSDAQ","price":2085,"change":29.74,"ratio":40.02,"volume":532356},{"code":"340440","name":"세림B&G","market":"KOSDAQ","price":924,"change":6.82,"ratio":38.65,"volume":4989310},{"code":"042040","name":"케이피엠테크","market":"KOSDAQ","price":5750,"change":-4.17,"ratio":38.04,"volume":1354637},{"code":"053290","name":"NE능률","market":"KOSDAQ","price":1451,"change":13.01,"ratio":29.38,"volume":511125},{"code":"003280","name":"흥아해운","market":"KOSPI","price":1610,"change":-2.42,"ratio":27.5,"volume":48774615},{"code":"065660","name":"안트로젠","market":"KOSDAQ","price":15350,"change":-29.91,"ratio":25.76,"volume":402738},{"code":"000440","name":"중앙에너비스","market":"KOSDAQ","price":13130,"change":1.08,"ratio":21.43,"volume":256662},{"code":"439090","name":"마녀공장","market":"KOSDAQ","price":17600,"change":18.44,"ratio":15.02,"volume":2418263},{"code":"109610","name":"에스와이","market":"KOSDAQ","price":2505,"change":-2.15,"ratio":13.85,"volume":16404410},{"code":"000067","name":"TIGER 차이나AI소프트웨어","market":"KOSPI","price":12920,"change":8.43,"ratio":12.71,"volume":146689},{"code":"263800","name":"데이타솔루션","market":"KOSDAQ","price":5940,"change":29.98,"ratio":11.51,"volume":625530},{"code":"252410","name":"RISE 200선물인버스","market":"KOSPI","price":1348,"change":5.64,"ratio":11.21,"volume":2120357},{"code":"368970","name":"오에스피","market":"KOSDAQ","price":2485,"change":0.0,"ratio":10.94,"volume":302514},{"code":"038110","name":"에코플라스틱","market":"KOSDAQ","price":2005,"change":1.21,"ratio":10.04,"volume":2263624},{"code":"045510","name":"정원엔시스","market":"KOSDAQ","price":725,"change":0.42,"ratio":9.87,"volume":190414},{"code":"005360","name":"모나미","market":"KOSPI","price":1369,"change":4.5,"ratio":9.44,"volume":240085},{"code":"067290","name":"JW신약","market":"KOSDAQ","price":1460,"change":1.11,"ratio":9.36,"volume":11838855},{"code":"469050","name":"RISE 미국반도체NYSE(H)","market":"KOSPI","price":32920,"change":-3.33,"ratio":9.35,"volume":197764},{"code":"008930","name":"한미사이언스","market":"KOSPI","price":33650,"change":6.32,"ratio":9.31,"volume":710813},{"code":"255220","name":"SG","market":"KOSDAQ","price":1489,"change":-1.33,"ratio":9.18,"volume":16934537},{"code":"064240","name":"홈캐스트","market":"KOSDAQ","price":1522,"change":-0.33,"ratio":9.16,"volume":249904},{"code":"320000","name":"한울반도체","market":"KOSDAQ","price":12420,"change":9.62,"ratio":9.04,"volume":1445677}]}