{"updated":"2026-05-13 20:44:02 KST","period":{"from":"20260506","to":"20260513"},"disclosures":[{"code":"096770","name":"SK이노베이션","report_nm":"[첨부정정]연결재무제표기준영업(잠정)실적(공정공시)              ","rcept_dt":"20260513","rcept_no":"20260513801240","url":"https://dart.fss.or.kr/dsaf001/main.do?rcpNo=20260513801240"},{"code":"481890","name":"엔에이치스팩31호","report_nm":"분기보고서 (2026.03)","rcept_dt":"20260513","rcept_no":"20260513000870","url":"https://dart.fss.or.kr/dsaf001/main.do?rcpNo=20260513000870"},{"code":"001740","name":"SK네트웍스","report_nm":"연결재무제표기준영업(잠정)실적(공정공시)              ","rcept_dt":"20260513","rcept_no":"20260513801148","url":"https://dart.fss.or.kr/dsaf001/main.do?rcpNo=20260513801148"},{"code":"042940","name":"상지건설","report_nm":"분기보고서 (2026.03)","rcept_dt":"20260513","rcept_no":"20260513000857","url":"https://dart.fss.or.kr/dsaf001/main.do?rcpNo=20260513000857"},{"code":"024060","name":"흥구석유","report_nm":"분기보고서 (2026.03)","rcept_dt":"20260513","rcept_no":"20260513000850","url":"https://dart.fss.or.kr/dsaf001/main.do?rcpNo=20260513000850"},{"code":"012200","name":"계양전기","report_nm":"분기보고서 (2026.03)","rcept_dt":"20260513","rcept_no":"20260513000845","url":"https://dart.fss.or.kr/dsaf001/main.do?rcpNo=20260513000845"},{"code":"451700","name":"엔에이치스팩29호","report_nm":"분기보고서 (2026.03)","rcept_dt":"20260513","rcept_no":"20260513000843","url":"https://dart.fss.or.kr/dsaf001/main.do?rcpNo=20260513000843"},{"code":"060150","name":"인선이엔티","report_nm":"분기보고서 (2026.03)","rcept_dt":"20260513","rcept_no":"20260513000837","url":"https://dart.fss.or.kr/dsaf001/main.do?rcpNo=20260513000837"},{"code":"452980","name":"신한제11호기업인수목적","report_nm":"분기보고서 (2026.03)","rcept_dt":"20260513","rcept_no":"20260513000836","url":"https://dart.fss.or.kr/dsaf001/main.do?rcpNo=20260513000836"},{"code":"083930","name":"아바코","report_nm":"분기보고서 (2026.03)","rcept_dt":"20260513","rcept_no":"20260513000826","url":"https://dart.fss.or.kr/dsaf001/main.do?rcpNo=20260513000826"},{"code":"117670","name":"알파칩스","report_nm":"분기보고서 (2026.03)","rcept_dt":"20260513","rcept_no":"20260513000818","url":"https://dart.fss.or.kr/dsaf001/main.do?rcpNo=20260513000818"},{"code":"136490","name":"선진","report_nm":"분기보고서 (2026.03)","rcept_dt":"20260513","rcept_no":"20260513000811","url":"https://dart.fss.or.kr/dsaf001/main.do?rcpNo=20260513000811"},{"code":"187220","name":"디티앤씨","report_nm":"[기재정정]사업보고서 (2025.12)","rcept_dt":"20260513","rcept_no":"20260513000805","url":"https://dart.fss.or.kr/dsaf001/main.do?rcpNo=20260513000805"},{"code":"285130","name":"SK케미칼","report_nm":"분기보고서 (2026.03)","rcept_dt":"20260513","rcept_no":"20260513000804","url":"https://dart.fss.or.kr/dsaf001/main.do?rcpNo=20260513000804"},{"code":"130660","name":"한전산업","report_nm":"분기보고서 (2026.03)","rcept_dt":"20260513","rcept_no":"20260513000798","url":"https://dart.fss.or.kr/dsaf001/main.do?rcpNo=20260513000798"},{"code":"481850","name":"신한글로벌액티브리츠","report_nm":"사업보고서 (2026.02)","rcept_dt":"20260513","rcept_no":"20260513000783","url":"https://dart.fss.or.kr/dsaf001/main.do?rcpNo=20260513000783"},{"code":"281820","name":"케이씨텍","report_nm":"분기보고서 (2026.03)","rcept_dt":"20260513","rcept_no":"20260513000773","url":"https://dart.fss.or.kr/dsaf001/main.do?rcpNo=20260513000773"},{"code":"007610","name":"선도전기","report_nm":"분기보고서 (2026.03)","rcept_dt":"20260513","rcept_no":"20260513000768","url":"https://dart.fss.or.kr/dsaf001/main.do?rcpNo=20260513000768"},{"code":"377460","name":"큐에이드","report_nm":"분기보고서 (2026.03)","rcept_dt":"20260513","rcept_no":"20260513000750","url":"https://dart.fss.or.kr/dsaf001/main.do?rcpNo=20260513000750"},{"code":"067290","name":"JW신약","report_nm":"영업(잠정)실적(공정공시)              ","rcept_dt":"20260513","rcept_no":"20260513900897","url":"https://dart.fss.or.kr/dsaf001/main.do?rcpNo=20260513900897"},{"code":"078520","name":"에이블씨엔씨","report_nm":"분기보고서 (2026.03)","rcept_dt":"20260513","rcept_no":"20260513000739","url":"https://dart.fss.or.kr/dsaf001/main.do?rcpNo=20260513000739"},{"code":"474660","name":"신한제12호스팩","report_nm":"분기보고서 (2026.03)","rcept_dt":"20260513","rcept_no":"20260513000737","url":"https://dart.fss.or.kr/dsaf001/main.do?rcpNo=20260513000737"},{"code":"489790","name":"한화비전","report_nm":"분기보고서 (2026.03)","rcept_dt":"20260513","rcept_no":"20260513000735","url":"https://dart.fss.or.kr/dsaf001/main.do?rcpNo=20260513000735"},{"code":"234080","name":"JW생명과학","report_nm":"영업(잠정)실적(공정공시)              ","rcept_dt":"20260513","rcept_no":"20260513800898","url":"https://dart.fss.or.kr/dsaf001/main.do?rcpNo=20260513800898"},{"code":"462350","name":"이노스페이스","report_nm":"분기보고서 (2026.03)","rcept_dt":"20260513","rcept_no":"20260513000718","url":"https://dart.fss.or.kr/dsaf001/main.do?rcpNo=20260513000718"},{"code":"060280","name":"큐렉소","report_nm":"분기보고서 (2026.03)","rcept_dt":"20260513","rcept_no":"20260513000715","url":"https://dart.fss.or.kr/dsaf001/main.do?rcpNo=20260513000715"},{"code":"009450","name":"경동나비엔","report_nm":"연결재무제표기준영업(잠정)실적(공정공시)              ","rcept_dt":"20260513","rcept_no":"20260513800863","url":"https://dart.fss.or.kr/dsaf001/main.do?rcpNo=20260513800863"},{"code":"189330","name":"씨이랩","report_nm":"분기보고서 (2026.03)","rcept_dt":"20260513","rcept_no":"20260513000709","url":"https://dart.fss.or.kr/dsaf001/main.do?rcpNo=20260513000709"},{"code":"457370","name":"한켐","report_nm":"분기보고서 (2026.03)","rcept_dt":"20260513","rcept_no":"20260513000707","url":"https://dart.fss.or.kr/dsaf001/main.do?rcpNo=20260513000707"},{"code":"272210","name":"한화시스템","report_nm":"분기보고서 (2026.03)","rcept_dt":"20260513","rcept_no":"20260513000702","url":"https://dart.fss.or.kr/dsaf001/main.do?rcpNo=20260513000702"},{"code":"033240","name":"자화전자","report_nm":"분기보고서 (2026.03)","rcept_dt":"20260513","rcept_no":"20260513000698","url":"https://dart.fss.or.kr/dsaf001/main.do?rcpNo=20260513000698"},{"code":"039130","name":"하나투어","report_nm":"연결재무제표기준영업(잠정)실적(공정공시)              ","rcept_dt":"20260513","rcept_no":"20260513800858","url":"https://dart.fss.or.kr/dsaf001/main.do?rcpNo=20260513800858"},{"code":"003070","name":"코오롱글로벌","report_nm":"연결재무제표기준영업(잠정)실적(공정공시)              ","rcept_dt":"20260513","rcept_no":"20260513800844","url":"https://dart.fss.or.kr/dsaf001/main.do?rcpNo=20260513800844"},{"code":"071950","name":"코아스","report_nm":"분기보고서 (2026.03)","rcept_dt":"20260513","rcept_no":"20260513000694","url":"https://dart.fss.or.kr/dsaf001/main.do?rcpNo=20260513000694"},{"code":"267850","name":"아시아나IDT","report_nm":"분기보고서 (2026.03)","rcept_dt":"20260513","rcept_no":"20260513000692","url":"https://dart.fss.or.kr/dsaf001/main.do?rcpNo=20260513000692"},{"code":"004710","name":"한솔테크닉스","report_nm":"분기보고서 (2026.03)","rcept_dt":"20260513","rcept_no":"20260513000689","url":"https://dart.fss.or.kr/dsaf001/main.do?rcpNo=20260513000689"},{"code":"462520","name":"조선내화","report_nm":"분기보고서 (2026.03)","rcept_dt":"20260513","rcept_no":"20260513000687","url":"https://dart.fss.or.kr/dsaf001/main.do?rcpNo=20260513000687"},{"code":"039490","name":"키움증권","report_nm":"분기보고서 (2026.03)","rcept_dt":"20260513","rcept_no":"20260513000684","url":"https://dart.fss.or.kr/dsaf001/main.do?rcpNo=20260513000684"},{"code":"136480","name":"하림","report_nm":"분기보고서 (2026.03)","rcept_dt":"20260513","rcept_no":"20260513000674","url":"https://dart.fss.or.kr/dsaf001/main.do?rcpNo=20260513000674"},{"code":"063080","name":"컴투스홀딩스","report_nm":"연결재무제표기준영업(잠정)실적(공정공시)              ","rcept_dt":"20260513","rcept_no":"20260513900771","url":"https://dart.fss.or.kr/dsaf001/main.do?rcpNo=20260513900771"},{"code":"183350","name":"엘피케이로보틱스","report_nm":"분기보고서 (2026.03)","rcept_dt":"20260513","rcept_no":"20260513000663","url":"https://dart.fss.or.kr/dsaf001/main.do?rcpNo=20260513000663"},{"code":"235980","name":"메드팩토","report_nm":"분기보고서 (2026.03)","rcept_dt":"20260513","rcept_no":"20260513000655","url":"https://dart.fss.or.kr/dsaf001/main.do?rcpNo=20260513000655"},{"code":"084370","name":"유진테크","report_nm":"분기보고서 (2026.03)","rcept_dt":"20260513","rcept_no":"20260513000654","url":"https://dart.fss.or.kr/dsaf001/main.do?rcpNo=20260513000654"},{"code":"036580","name":"팜스코","report_nm":"분기보고서 (2026.03)","rcept_dt":"20260513","rcept_no":"20260513000653","url":"https://dart.fss.or.kr/dsaf001/main.do?rcpNo=20260513000653"},{"code":"361610","name":"SK아이이테크놀로지","report_nm":"연결재무제표기준영업(잠정)실적(공정공시)              ","rcept_dt":"20260513","rcept_no":"20260513800773","url":"https://dart.fss.or.kr/dsaf001/main.do?rcpNo=20260513800773"},{"code":"272210","name":"한화시스템","report_nm":"[기재정정]사업보고서 (2025.12)","rcept_dt":"20260513","rcept_no":"20260513000644","url":"https://dart.fss.or.kr/dsaf001/main.do?rcpNo=20260513000644"},{"code":"236200","name":"슈프리마","report_nm":"분기보고서 (2026.03)","rcept_dt":"20260513","rcept_no":"20260513000643","url":"https://dart.fss.or.kr/dsaf001/main.do?rcpNo=20260513000643"},{"code":"487360","name":"신한제14호스팩","report_nm":"[기재정정]분기보고서 (2026.03)","rcept_dt":"20260513","rcept_no":"20260513000640","url":"https://dart.fss.or.kr/dsaf001/main.do?rcpNo=20260513000640"},{"code":"496070","name":"신한제16호스팩","report_nm":"분기보고서 (2026.03)","rcept_dt":"20260513","rcept_no":"20260513000634","url":"https://dart.fss.or.kr/dsaf001/main.do?rcpNo=20260513000634"},{"code":"047920","name":"HLB제약","report_nm":"분기보고서 (2026.03)","rcept_dt":"20260513","rcept_no":"20260513000629","url":"https://dart.fss.or.kr/dsaf001/main.do?rcpNo=20260513000629"},{"code":"092130","name":"이크레더블","report_nm":"분기보고서 (2026.03)","rcept_dt":"20260513","rcept_no":"20260513000624","url":"https://dart.fss.or.kr/dsaf001/main.do?rcpNo=20260513000624"},{"code":"237880","name":"클리오","report_nm":"분기보고서 (2026.03)","rcept_dt":"20260513","rcept_no":"20260513000622","url":"https://dart.fss.or.kr/dsaf001/main.do?rcpNo=20260513000622"},{"code":"487830","name":"신한제15호스팩","report_nm":"분기보고서 (2026.03)","rcept_dt":"20260513","rcept_no":"20260513000620","url":"https://dart.fss.or.kr/dsaf001/main.do?rcpNo=20260513000620"},{"code":"302440","name":"SK바이오사이언스","report_nm":"분기보고서 (2026.03)","rcept_dt":"20260513","rcept_no":"20260513000618","url":"https://dart.fss.or.kr/dsaf001/main.do?rcpNo=20260513000618"},{"code":"121890","name":"에스디시스템","report_nm":"분기보고서 (2026.03)","rcept_dt":"20260513","rcept_no":"20260513000616","url":"https://dart.fss.or.kr/dsaf001/main.do?rcpNo=20260513000616"},{"code":"239340","name":"이스트에이드","report_nm":"분기보고서 (2026.03)","rcept_dt":"20260513","rcept_no":"20260513000612","url":"https://dart.fss.or.kr/dsaf001/main.do?rcpNo=20260513000612"},{"code":"214370","name":"케어젠","report_nm":"분기보고서 (2026.03)","rcept_dt":"20260513","rcept_no":"20260513000610","url":"https://dart.fss.or.kr/dsaf001/main.do?rcpNo=20260513000610"},{"code":"094840","name":"슈프리마에이치큐","report_nm":"분기보고서 (2026.03)","rcept_dt":"20260513","rcept_no":"20260513000601","url":"https://dart.fss.or.kr/dsaf001/main.do?rcpNo=20260513000601"},{"code":"095720","name":"웅진씽크빅","report_nm":"연결재무제표기준영업(잠정)실적(공정공시)              ","rcept_dt":"20260513","rcept_no":"20260513800722","url":"https://dart.fss.or.kr/dsaf001/main.do?rcpNo=20260513800722"},{"code":"035000","name":"HS애드","report_nm":"연결재무제표기준영업(잠정)실적(공정공시)              ","rcept_dt":"20260513","rcept_no":"20260513800706","url":"https://dart.fss.or.kr/dsaf001/main.do?rcpNo=20260513800706"},{"code":"474930","name":"신한제13호스팩","report_nm":"분기보고서 (2026.03)","rcept_dt":"20260513","rcept_no":"20260513000591","url":"https://dart.fss.or.kr/dsaf001/main.do?rcpNo=20260513000591"},{"code":"183490","name":"엔지켐생명과학","report_nm":"분기보고서 (2026.03)","rcept_dt":"20260513","rcept_no":"20260513000589","url":"https://dart.fss.or.kr/dsaf001/main.do?rcpNo=20260513000589"},{"code":"179290","name":"엠아이텍","report_nm":"분기보고서 (2026.03)","rcept_dt":"20260513","rcept_no":"20260513000586","url":"https://dart.fss.or.kr/dsaf001/main.do?rcpNo=20260513000586"},{"code":"073490","name":"LIG아큐버","report_nm":"분기보고서 (2026.03)","rcept_dt":"20260513","rcept_no":"20260513000575","url":"https://dart.fss.or.kr/dsaf001/main.do?rcpNo=20260513000575"},{"code":"015760","name":"한국전력공사","report_nm":"연결재무제표기준영업(잠정)실적(공정공시)              ","rcept_dt":"20260513","rcept_no":"20260513800695","url":"https://dart.fss.or.kr/dsaf001/main.do?rcpNo=20260513800695"},{"code":"003230","name":"삼양식품","report_nm":"분기보고서 (2026.03)","rcept_dt":"20260513","rcept_no":"20260513000571","url":"https://dart.fss.or.kr/dsaf001/main.do?rcpNo=20260513000571"},{"code":"208710","name":"포톤","report_nm":"분기보고서 (2026.03)","rcept_dt":"20260513","rcept_no":"20260513000567","url":"https://dart.fss.or.kr/dsaf001/main.do?rcpNo=20260513000567"},{"code":"079940","name":"가비아","report_nm":"연결재무제표기준영업(잠정)실적(공정공시)              ","rcept_dt":"20260513","rcept_no":"20260513900642","url":"https://dart.fss.or.kr/dsaf001/main.do?rcpNo=20260513900642"},{"code":"079940","name":"가비아","report_nm":"영업(잠정)실적(공정공시)              ","rcept_dt":"20260513","rcept_no":"20260513900638","url":"https://dart.fss.or.kr/dsaf001/main.do?rcpNo=20260513900638"},{"code":"258790","name":"소프트캠프","report_nm":"분기보고서 (2026.03)","rcept_dt":"20260513","rcept_no":"20260513000559","url":"https://dart.fss.or.kr/dsaf001/main.do?rcpNo=20260513000559"},{"code":"370090","name":"퓨런티어","report_nm":"분기보고서 (2026.03)","rcept_dt":"20260513","rcept_no":"20260513000557","url":"https://dart.fss.or.kr/dsaf001/main.do?rcpNo=20260513000557"},{"code":"000240","name":"한국앤컴퍼니","report_nm":"연결재무제표기준영업(잠정)실적(공정공시)              ","rcept_dt":"20260513","rcept_no":"20260513800632","url":"https://dart.fss.or.kr/dsaf001/main.do?rcpNo=20260513800632"},{"code":"042660","name":"한화오션","report_nm":"분기보고서 (2026.03)","rcept_dt":"20260513","rcept_no":"20260513000552","url":"https://dart.fss.or.kr/dsaf001/main.do?rcpNo=20260513000552"},{"code":"096770","name":"SK이노베이션","report_nm":"연결재무제표기준영업(잠정)실적(공정공시)              ","rcept_dt":"20260513","rcept_no":"20260513800630","url":"https://dart.fss.or.kr/dsaf001/main.do?rcpNo=20260513800630"},{"code":"005860","name":"한일사료","report_nm":"분기보고서 (2026.03)","rcept_dt":"20260513","rcept_no":"20260513000548","url":"https://dart.fss.or.kr/dsaf001/main.do?rcpNo=20260513000548"},{"code":"298690","name":"에어부산","report_nm":"분기보고서 (2026.03)","rcept_dt":"20260513","rcept_no":"20260513000540","url":"https://dart.fss.or.kr/dsaf001/main.do?rcpNo=20260513000540"},{"code":"145270","name":"케이탑리츠","report_nm":"분기보고서 (2026.03)","rcept_dt":"20260513","rcept_no":"20260513000530","url":"https://dart.fss.or.kr/dsaf001/main.do?rcpNo=20260513000530"},{"code":"177830","name":"파버나인","report_nm":"분기보고서 (2026.03)","rcept_dt":"20260513","rcept_no":"20260513000528","url":"https://dart.fss.or.kr/dsaf001/main.do?rcpNo=20260513000528"},{"code":"335890","name":"비올메디컬","report_nm":"분기보고서 (2026.03)","rcept_dt":"20260513","rcept_no":"20260513000515","url":"https://dart.fss.or.kr/dsaf001/main.do?rcpNo=20260513000515"},{"code":"058480","name":"해원에스티","report_nm":"분기보고서 (2026.03)","rcept_dt":"20260513","rcept_no":"20260513000502","url":"https://dart.fss.or.kr/dsaf001/main.do?rcpNo=20260513000502"},{"code":"068100","name":"케이웨더","report_nm":"분기보고서 (2026.03)","rcept_dt":"20260513","rcept_no":"20260513000501","url":"https://dart.fss.or.kr/dsaf001/main.do?rcpNo=20260513000501"},{"code":"065310","name":"더스텔라","report_nm":"분기보고서 (2026.03)","rcept_dt":"20260513","rcept_no":"20260513000492","url":"https://dart.fss.or.kr/dsaf001/main.do?rcpNo=20260513000492"},{"code":"000230","name":"일동홀딩스","report_nm":"연결재무제표기준영업(잠정)실적(공정공시)              ","rcept_dt":"20260513","rcept_no":"20260513800562","url":"https://dart.fss.or.kr/dsaf001/main.do?rcpNo=20260513800562"},{"code":"003800","name":"에이스침대","report_nm":"분기보고서 (2026.03)","rcept_dt":"20260513","rcept_no":"20260513000487","url":"https://dart.fss.or.kr/dsaf001/main.do?rcpNo=20260513000487"},{"code":"011200","name":"HMM","report_nm":"분기보고서 (2026.03)","rcept_dt":"20260513","rcept_no":"20260513000483","url":"https://dart.fss.or.kr/dsaf001/main.do?rcpNo=20260513000483"},{"code":"054670","name":"대한뉴팜","report_nm":"분기보고서 (2026.03)","rcept_dt":"20260513","rcept_no":"20260513000480","url":"https://dart.fss.or.kr/dsaf001/main.do?rcpNo=20260513000480"},{"code":"388610","name":"지에프씨생명과학","report_nm":"분기보고서 (2026.03)","rcept_dt":"20260513","rcept_no":"20260513000465","url":"https://dart.fss.or.kr/dsaf001/main.do?rcpNo=20260513000465"},{"code":"033550","name":"일레덱스홀딩스","report_nm":"분기보고서 (2026.03)","rcept_dt":"20260513","rcept_no":"20260513000462","url":"https://dart.fss.or.kr/dsaf001/main.do?rcpNo=20260513000462"},{"code":"249420","name":"일동제약","report_nm":"연결재무제표기준영업(잠정)실적(공정공시)              ","rcept_dt":"20260513","rcept_no":"20260513800538","url":"https://dart.fss.or.kr/dsaf001/main.do?rcpNo=20260513800538"},{"code":"389140","name":"포바이포","report_nm":"분기보고서 (2026.03)","rcept_dt":"20260513","rcept_no":"20260513000440","url":"https://dart.fss.or.kr/dsaf001/main.do?rcpNo=20260513000440"},{"code":"241770","name":"메카로","report_nm":"분기보고서 (2026.03)","rcept_dt":"20260513","rcept_no":"20260513000436","url":"https://dart.fss.or.kr/dsaf001/main.do?rcpNo=20260513000436"},{"code":"434480","name":"모니터랩","report_nm":"분기보고서 (2026.03)","rcept_dt":"20260513","rcept_no":"20260513000430","url":"https://dart.fss.or.kr/dsaf001/main.do?rcpNo=20260513000430"},{"code":"010780","name":"아이에스동서","report_nm":"분기보고서 (2026.03)","rcept_dt":"20260513","rcept_no":"20260513000426","url":"https://dart.fss.or.kr/dsaf001/main.do?rcpNo=20260513000426"},{"code":"267250","name":"HD현대","report_nm":"연결재무제표기준영업(잠정)실적(공정공시)              ","rcept_dt":"20260513","rcept_no":"20260513800488","url":"https://dart.fss.or.kr/dsaf001/main.do?rcpNo=20260513800488"},{"code":"267250","name":"HD현대","report_nm":"연결재무제표기준영업(잠정)실적(공정공시)(자회사의 주요경영사항)              ","rcept_dt":"20260513","rcept_no":"20260513800475","url":"https://dart.fss.or.kr/dsaf001/main.do?rcpNo=20260513800475"},{"code":"099320","name":"쎄트렉아이","report_nm":"분기보고서 (2026.03)","rcept_dt":"20260513","rcept_no":"20260513000409","url":"https://dart.fss.or.kr/dsaf001/main.do?rcpNo=20260513000409"},{"code":"200780","name":"비씨월드제약","report_nm":"분기보고서 (2026.03)","rcept_dt":"20260513","rcept_no":"20260513000405","url":"https://dart.fss.or.kr/dsaf001/main.do?rcpNo=20260513000405"},{"code":"376290","name":"씨유테크","report_nm":"분기보고서 (2026.03)","rcept_dt":"20260513","rcept_no":"20260513000394","url":"https://dart.fss.or.kr/dsaf001/main.do?rcpNo=20260513000394"},{"code":"024950","name":"삼천리자전거","report_nm":"분기보고서 (2026.03)","rcept_dt":"20260513","rcept_no":"20260513000393","url":"https://dart.fss.or.kr/dsaf001/main.do?rcpNo=20260513000393"},{"code":"265740","name":"엔에프씨","report_nm":"분기보고서 (2026.03)","rcept_dt":"20260513","rcept_no":"20260513000392","url":"https://dart.fss.or.kr/dsaf001/main.do?rcpNo=20260513000392"},{"code":"094850","name":"참좋은여행","report_nm":"분기보고서 (2026.03)","rcept_dt":"20260513","rcept_no":"20260513000368","url":"https://dart.fss.or.kr/dsaf001/main.do?rcpNo=20260513000368"},{"code":"071320","name":"지역난방공사","report_nm":"[기재정정]분기보고서 (2026.03)","rcept_dt":"20260513","rcept_no":"20260513000363","url":"https://dart.fss.or.kr/dsaf001/main.do?rcpNo=20260513000363"},{"code":"055490","name":"테이팩스","report_nm":"분기보고서 (2026.03)","rcept_dt":"20260513","rcept_no":"20260513000358","url":"https://dart.fss.or.kr/dsaf001/main.do?rcpNo=20260513000358"},{"code":"114810","name":"한솔아이원스","report_nm":"분기보고서 (2026.03)","rcept_dt":"20260513","rcept_no":"20260513000357","url":"https://dart.fss.or.kr/dsaf001/main.do?rcpNo=20260513000357"},{"code":"483650","name":"달바글로벌","report_nm":"분기보고서 (2026.03)","rcept_dt":"20260513","rcept_no":"20260513000356","url":"https://dart.fss.or.kr/dsaf001/main.do?rcpNo=20260513000356"},{"code":"036620","name":"감성코퍼레이션","report_nm":"분기보고서 (2026.03)","rcept_dt":"20260513","rcept_no":"20260513000342","url":"https://dart.fss.or.kr/dsaf001/main.do?rcpNo=20260513000342"},{"code":"036460","name":"한국가스공사","report_nm":"연결재무제표기준영업(잠정)실적(공정공시)              ","rcept_dt":"20260513","rcept_no":"20260513800420","url":"https://dart.fss.or.kr/dsaf001/main.do?rcpNo=20260513800420"},{"code":"016580","name":"환인제약","report_nm":"분기보고서 (2026.03)","rcept_dt":"20260513","rcept_no":"20260513000328","url":"https://dart.fss.or.kr/dsaf001/main.do?rcpNo=20260513000328"},{"code":"053160","name":"프리엠스","report_nm":"분기보고서 (2026.03)","rcept_dt":"20260513","rcept_no":"20260513000323","url":"https://dart.fss.or.kr/dsaf001/main.do?rcpNo=20260513000323"},{"code":"336570","name":"원텍","report_nm":"분기보고서 (2026.03)","rcept_dt":"20260513","rcept_no":"20260513000311","url":"https://dart.fss.or.kr/dsaf001/main.do?rcpNo=20260513000311"},{"code":"030520","name":"한글과컴퓨터","report_nm":"분기보고서 (2026.03)","rcept_dt":"20260513","rcept_no":"20260513000306","url":"https://dart.fss.or.kr/dsaf001/main.do?rcpNo=20260513000306"},{"code":"004430","name":"송원산업","report_nm":"분기보고서 (2026.03)","rcept_dt":"20260513","rcept_no":"20260513000304","url":"https://dart.fss.or.kr/dsaf001/main.do?rcpNo=20260513000304"},{"code":"025770","name":"한국정보통신","report_nm":"분기보고서 (2026.03)","rcept_dt":"20260513","rcept_no":"20260513000302","url":"https://dart.fss.or.kr/dsaf001/main.do?rcpNo=20260513000302"},{"code":"307180","name":"아이엘","report_nm":"분기보고서 (2026.03)","rcept_dt":"20260513","rcept_no":"20260513000301","url":"https://dart.fss.or.kr/dsaf001/main.do?rcpNo=20260513000301"},{"code":"331520","name":"밸로프","report_nm":"분기보고서 (2026.03)","rcept_dt":"20260513","rcept_no":"20260513000299","url":"https://dart.fss.or.kr/dsaf001/main.do?rcpNo=20260513000299"},{"code":"067920","name":"이글루","report_nm":"분기보고서 (2026.03)","rcept_dt":"20260513","rcept_no":"20260513000297","url":"https://dart.fss.or.kr/dsaf001/main.do?rcpNo=20260513000297"},{"code":"139480","name":"이마트","report_nm":"영업(잠정)실적(공정공시)              ","rcept_dt":"20260513","rcept_no":"20260513800396","url":"https://dart.fss.or.kr/dsaf001/main.do?rcpNo=20260513800396"},{"code":"139480","name":"이마트","report_nm":"연결재무제표기준영업(잠정)실적(공정공시)              ","rcept_dt":"20260513","rcept_no":"20260513800392","url":"https://dart.fss.or.kr/dsaf001/main.do?rcpNo=20260513800392"},{"code":"186230","name":"그린플러스","report_nm":"분기보고서 (2026.03)","rcept_dt":"20260513","rcept_no":"20260513000293","url":"https://dart.fss.or.kr/dsaf001/main.do?rcpNo=20260513000293"},{"code":"477470","name":"미래에셋비전스팩5호","report_nm":"분기보고서 (2026.03)","rcept_dt":"20260513","rcept_no":"20260513000291","url":"https://dart.fss.or.kr/dsaf001/main.do?rcpNo=20260513000291"},{"code":"487360","name":"신한제14호스팩","report_nm":"분기보고서 (2026.03)","rcept_dt":"20260513","rcept_no":"20260513000286","url":"https://dart.fss.or.kr/dsaf001/main.do?rcpNo=20260513000286"},{"code":"053290","name":"NE능률","report_nm":"영업(잠정)실적(공정공시)              ","rcept_dt":"20260513","rcept_no":"20260513900379","url":"https://dart.fss.or.kr/dsaf001/main.do?rcpNo=20260513900379"},{"code":"221800","name":"지구홀딩스","report_nm":"연결재무제표기준영업(잠정)실적(공정공시)              ","rcept_dt":"20260513","rcept_no":"20260513900367","url":"https://dart.fss.or.kr/dsaf001/main.do?rcpNo=20260513900367"},{"code":"033100","name":"제룡전기","report_nm":"분기보고서 (2026.03)","rcept_dt":"20260513","rcept_no":"20260513000274","url":"https://dart.fss.or.kr/dsaf001/main.do?rcpNo=20260513000274"},{"code":"481070","name":"에이유브랜즈","report_nm":"연결재무제표기준영업실적등에대한전망(공정공시)              ","rcept_dt":"20260513","rcept_no":"20260513900345","url":"https://dart.fss.or.kr/dsaf001/main.do?rcpNo=20260513900345"},{"code":"094820","name":"일진파워","report_nm":"분기보고서 (2026.03)","rcept_dt":"20260513","rcept_no":"20260513000261","url":"https://dart.fss.or.kr/dsaf001/main.do?rcpNo=20260513000261"},{"code":"215480","name":"토박스코리아","report_nm":"분기보고서 (2026.03)","rcept_dt":"20260513","rcept_no":"20260513000260","url":"https://dart.fss.or.kr/dsaf001/main.do?rcpNo=20260513000260"},{"code":"065620","name":"제낙스","report_nm":"분기보고서 (2026.03)","rcept_dt":"20260513","rcept_no":"20260513000258","url":"https://dart.fss.or.kr/dsaf001/main.do?rcpNo=20260513000258"},{"code":"147830","name":"제룡산업","report_nm":"분기보고서 (2026.03)","rcept_dt":"20260513","rcept_no":"20260513000255","url":"https://dart.fss.or.kr/dsaf001/main.do?rcpNo=20260513000255"},{"code":"025560","name":"미래산업","report_nm":"분기보고서 (2026.03)","rcept_dt":"20260513","rcept_no":"20260513000253","url":"https://dart.fss.or.kr/dsaf001/main.do?rcpNo=20260513000253"},{"code":"024880","name":"케이피에프","report_nm":"분기보고서 (2026.03)","rcept_dt":"20260513","rcept_no":"20260513000251","url":"https://dart.fss.or.kr/dsaf001/main.do?rcpNo=20260513000251"},{"code":"033830","name":"티비씨","report_nm":"분기보고서 (2026.03)","rcept_dt":"20260513","rcept_no":"20260513000242","url":"https://dart.fss.or.kr/dsaf001/main.do?rcpNo=20260513000242"},{"code":"075180","name":"새론오토모티브","report_nm":"분기보고서 (2026.03)","rcept_dt":"20260513","rcept_no":"20260513000234","url":"https://dart.fss.or.kr/dsaf001/main.do?rcpNo=20260513000234"},{"code":"020120","name":"키다리스튜디오","report_nm":"연결재무제표기준영업(잠정)실적(공정공시)              ","rcept_dt":"20260513","rcept_no":"20260513800328","url":"https://dart.fss.or.kr/dsaf001/main.do?rcpNo=20260513800328"},{"code":"060260","name":"뉴보텍","report_nm":"분기보고서 (2026.03)","rcept_dt":"20260513","rcept_no":"20260513000226","url":"https://dart.fss.or.kr/dsaf001/main.do?rcpNo=20260513000226"},{"code":"477380","name":"미래에셋비전스팩4호","report_nm":"분기보고서 (2026.03)","rcept_dt":"20260513","rcept_no":"20260513000224","url":"https://dart.fss.or.kr/dsaf001/main.do?rcpNo=20260513000224"},{"code":"078930","name":"GS","report_nm":"연결재무제표기준영업(잠정)실적(공정공시)              ","rcept_dt":"20260513","rcept_no":"20260513800309","url":"https://dart.fss.or.kr/dsaf001/main.do?rcpNo=20260513800309"},{"code":"307930","name":"컴퍼니케이","report_nm":"분기보고서 (2026.03)","rcept_dt":"20260513","rcept_no":"20260513000221","url":"https://dart.fss.or.kr/dsaf001/main.do?rcpNo=20260513000221"},{"code":"214150","name":"클래시스","report_nm":"연결재무제표기준영업(잠정)실적(공정공시)              ","rcept_dt":"20260513","rcept_no":"20260513900311","url":"https://dart.fss.or.kr/dsaf001/main.do?rcpNo=20260513900311"},{"code":"481070","name":"에이유브랜즈","report_nm":"연결재무제표기준영업(잠정)실적(공정공시)              ","rcept_dt":"20260513","rcept_no":"20260513900307","url":"https://dart.fss.or.kr/dsaf001/main.do?rcpNo=20260513900307"},{"code":"393210","name":"토마토시스템","report_nm":"분기보고서 (2026.03)","rcept_dt":"20260513","rcept_no":"20260513000206","url":"https://dart.fss.or.kr/dsaf001/main.do?rcpNo=20260513000206"},{"code":"484120","name":"도우인시스","report_nm":"분기보고서 (2026.03)","rcept_dt":"20260513","rcept_no":"20260513000195","url":"https://dart.fss.or.kr/dsaf001/main.do?rcpNo=20260513000195"},{"code":"301300","name":"바이브컴퍼니","report_nm":"분기보고서 (2026.03)","rcept_dt":"20260513","rcept_no":"20260513000191","url":"https://dart.fss.or.kr/dsaf001/main.do?rcpNo=20260513000191"},{"code":"058610","name":"에스피지","report_nm":"연결재무제표기준영업(잠정)실적(공정공시)              ","rcept_dt":"20260513","rcept_no":"20260513900250","url":"https://dart.fss.or.kr/dsaf001/main.do?rcpNo=20260513900250"},{"code":"073010","name":"케이에스피","report_nm":"분기보고서 (2026.03)","rcept_dt":"20260513","rcept_no":"20260513000183","url":"https://dart.fss.or.kr/dsaf001/main.do?rcpNo=20260513000183"},{"code":"251120","name":"바이오에프디엔씨","report_nm":"분기보고서 (2026.03)","rcept_dt":"20260513","rcept_no":"20260513000182","url":"https://dart.fss.or.kr/dsaf001/main.do?rcpNo=20260513000182"},{"code":"036640","name":"HRS","report_nm":"분기보고서 (2026.03)","rcept_dt":"20260513","rcept_no":"20260513000178","url":"https://dart.fss.or.kr/dsaf001/main.do?rcpNo=20260513000178"},{"code":"257370","name":"피엔티엠에스","report_nm":"분기보고서 (2026.03)","rcept_dt":"20260513","rcept_no":"20260513000169","url":"https://dart.fss.or.kr/dsaf001/main.do?rcpNo=20260513000169"},{"code":"016670","name":"디모아","report_nm":"분기보고서 (2026.03)","rcept_dt":"20260513","rcept_no":"20260513000168","url":"https://dart.fss.or.kr/dsaf001/main.do?rcpNo=20260513000168"},{"code":"261200","name":"덴티스","report_nm":"분기보고서 (2026.03)","rcept_dt":"20260513","rcept_no":"20260513000159","url":"https://dart.fss.or.kr/dsaf001/main.do?rcpNo=20260513000159"},{"code":"095610","name":"테스","report_nm":"분기보고서 (2026.03)","rcept_dt":"20260513","rcept_no":"20260513000153","url":"https://dart.fss.or.kr/dsaf001/main.do?rcpNo=20260513000153"},{"code":"002760","name":"보락","report_nm":"분기보고서 (2026.03)","rcept_dt":"20260513","rcept_no":"20260513000143","url":"https://dart.fss.or.kr/dsaf001/main.do?rcpNo=20260513000143"},{"code":"273060","name":"와이즈버즈","report_nm":"분기보고서 (2026.03)","rcept_dt":"20260513","rcept_no":"20260513000140","url":"https://dart.fss.or.kr/dsaf001/main.do?rcpNo=20260513000140"},{"code":"377740","name":"바이오노트","report_nm":"연결재무제표기준영업(잠정)실적(공정공시)              ","rcept_dt":"20260513","rcept_no":"20260513800204","url":"https://dart.fss.or.kr/dsaf001/main.do?rcpNo=20260513800204"},{"code":"372910","name":"한컴라이프케어","report_nm":"분기보고서 (2026.03)","rcept_dt":"20260513","rcept_no":"20260513000133","url":"https://dart.fss.or.kr/dsaf001/main.do?rcpNo=20260513000133"},{"code":"170790","name":"파이오링크","report_nm":"분기보고서 (2026.03)","rcept_dt":"20260513","rcept_no":"20260513000130","url":"https://dart.fss.or.kr/dsaf001/main.do?rcpNo=20260513000130"},{"code":"071320","name":"지역난방공사","report_nm":"분기보고서 (2026.03)","rcept_dt":"20260513","rcept_no":"20260513000123","url":"https://dart.fss.or.kr/dsaf001/main.do?rcpNo=20260513000123"},{"code":"039840","name":"디오","report_nm":"분기보고서 (2026.03)","rcept_dt":"20260513","rcept_no":"20260513000104","url":"https://dart.fss.or.kr/dsaf001/main.do?rcpNo=20260513000104"},{"code":"137400","name":"피엔티","report_nm":"분기보고서 (2026.03)","rcept_dt":"20260513","rcept_no":"20260513000102","url":"https://dart.fss.or.kr/dsaf001/main.do?rcpNo=20260513000102"},{"code":"013720","name":"THE CUBE&","report_nm":"분기보고서 (2026.03)","rcept_dt":"20260513","rcept_no":"20260513000100","url":"https://dart.fss.or.kr/dsaf001/main.do?rcpNo=20260513000100"},{"code":"096350","name":"대창솔루션","report_nm":"분기보고서 (2026.03)","rcept_dt":"20260513","rcept_no":"20260513000097","url":"https://dart.fss.or.kr/dsaf001/main.do?rcpNo=20260513000097"},{"code":"073190","name":"듀오백","report_nm":"분기보고서 (2026.03)","rcept_dt":"20260513","rcept_no":"20260513000082","url":"https://dart.fss.or.kr/dsaf001/main.do?rcpNo=20260513000082"},{"code":"204840","name":"지엘팜텍","report_nm":"분기보고서 (2026.03)","rcept_dt":"20260513","rcept_no":"20260513000078","url":"https://dart.fss.or.kr/dsaf001/main.do?rcpNo=20260513000078"},{"code":"467930","name":"IBKS제23호스팩","report_nm":"분기보고서 (2026.03)","rcept_dt":"20260513","rcept_no":"20260513000043","url":"https://dart.fss.or.kr/dsaf001/main.do?rcpNo=20260513000043"},{"code":"214430","name":"아이쓰리시스템","report_nm":"[기재정정]분기보고서 (2026.03)","rcept_dt":"20260513","rcept_no":"20260513000041","url":"https://dart.fss.or.kr/dsaf001/main.do?rcpNo=20260513000041"},{"code":"078340","name":"컴투스","report_nm":"영업(잠정)실적(공정공시)              ","rcept_dt":"20260513","rcept_no":"20260513900110","url":"https://dart.fss.or.kr/dsaf001/main.do?rcpNo=20260513900110"},{"code":"078340","name":"컴투스","report_nm":"연결재무제표기준영업(잠정)실적(공정공시)              ","rcept_dt":"20260513","rcept_no":"20260513900109","url":"https://dart.fss.or.kr/dsaf001/main.do?rcpNo=20260513900109"},{"code":"058110","name":"멕아이씨에스","report_nm":"분기보고서 (2026.03)","rcept_dt":"20260513","rcept_no":"20260513000037","url":"https://dart.fss.or.kr/dsaf001/main.do?rcpNo=20260513000037"},{"code":"263020","name":"디케이앤디","report_nm":"분기보고서 (2026.03)","rcept_dt":"20260513","rcept_no":"20260513000033","url":"https://dart.fss.or.kr/dsaf001/main.do?rcpNo=20260513000033"},{"code":"214430","name":"아이쓰리시스템","report_nm":"분기보고서 (2026.03)","rcept_dt":"20260513","rcept_no":"20260513000028","url":"https://dart.fss.or.kr/dsaf001/main.do?rcpNo=20260513000028"},{"code":"000120","name":"CJ대한통운","report_nm":"연결재무제표기준영업(잠정)실적(공정공시)              ","rcept_dt":"20260513","rcept_no":"20260513800102","url":"https://dart.fss.or.kr/dsaf001/main.do?rcpNo=20260513800102"},{"code":"054090","name":"삼진엘앤디","report_nm":"분기보고서 (2026.03)","rcept_dt":"20260513","rcept_no":"20260513000016","url":"https://dart.fss.or.kr/dsaf001/main.do?rcpNo=20260513000016"},{"code":"417840","name":"저스템","report_nm":"분기보고서 (2026.03)","rcept_dt":"20260513","rcept_no":"20260513000015","url":"https://dart.fss.or.kr/dsaf001/main.do?rcpNo=20260513000015"},{"code":"440320","name":"오픈놀","report_nm":"분기보고서 (2026.03)","rcept_dt":"20260513","rcept_no":"20260513000013","url":"https://dart.fss.or.kr/dsaf001/main.do?rcpNo=20260513000013"},{"code":"487720","name":"키움제10호스팩","report_nm":"분기보고서 (2026.03)","rcept_dt":"20260513","rcept_no":"20260513000012","url":"https://dart.fss.or.kr/dsaf001/main.do?rcpNo=20260513000012"},{"code":"036570","name":"NC","report_nm":"연결재무제표기준영업(잠정)실적(공정공시)              ","rcept_dt":"20260513","rcept_no":"20260513800029","url":"https://dart.fss.or.kr/dsaf001/main.do?rcpNo=20260513800029"},{"code":"192080","name":"더블유게임즈","report_nm":"연결재무제표기준영업(잠정)실적(공정공시)              ","rcept_dt":"20260513","rcept_no":"20260513800025","url":"https://dart.fss.or.kr/dsaf001/main.do?rcpNo=20260513800025"},{"code":"192080","name":"더블유게임즈","report_nm":"영업(잠정)실적(공정공시)              ","rcept_dt":"20260513","rcept_no":"20260513800020","url":"https://dart.fss.or.kr/dsaf001/main.do?rcpNo=20260513800020"},{"code":"083500","name":"에프엔에스테크","report_nm":"분기보고서 (2026.03)","rcept_dt":"20260513","rcept_no":"20260513000010","url":"https://dart.fss.or.kr/dsaf001/main.do?rcpNo=20260513000010"},{"code":"405100","name":"큐알티","report_nm":"분기보고서 (2026.03)","rcept_dt":"20260513","rcept_no":"20260513000009","url":"https://dart.fss.or.kr/dsaf001/main.do?rcpNo=20260513000009"}]}